spiir_p_astro-1.0.1-py3.10-nspkg.pth
doc/conf.py
etc/conf.ini
ligo/p_astro/__init__.py
ligo/p_astro/computation.py
ligo/p_astro/gstlal_utils.py
ligo/p_astro/utils.py
ligo/p_astro/data/H1L1V1-mean_counts-1126051217-61603201.json
ligo/p_astro/data/H1L1V1-pipeline-far_snr-thresholds.json
ligo/p_astro/data/H1L1V1-weights-bins_686-1126051217-61603201.json
ligo/p_astro/data/__init__.py
ligo/p_astro/data/p_astro_livetime.json
ligo/p_astro/tests/__init__.py
ligo/p_astro/tests/test_p_astro.py
ligo/p_astro/tests/test_p_astro_computation.py
ligo/p_astro/tests/test_p_astro_gstlal.py
ligo/p_astro/tests/data/__init__.py
ligo/p_astro/tests/data/background_hits.txt
ligo/p_astro/tests/data/bbh_wellfound_hits.txt
ligo/p_astro/tests/data/bns_wellfound_hits.txt
ligo/p_astro/tests/data/coinc.xml
ligo/p_astro/tests/data/coinc_G322589.xml
ligo/p_astro/tests/data/coinc_G5351.xml
ligo/p_astro/tests/data/f_divby_b.txt
ligo/p_astro/tests/data/nsbh_wellfound_hits.txt
ligo/p_astro/tests/data/ranking_data_G322589.xml.gz
ligo/p_astro/tests/data/zerolag_svd_bank_nums.txt
spiir_p_astro-1.0.1.dist-info/LICENSE
spiir_p_astro-1.0.1.dist-info/METADATA
spiir_p_astro-1.0.1.dist-info/WHEEL
spiir_p_astro-1.0.1.dist-info/entry_points.txt
spiir_p_astro-1.0.1.dist-info/namespace_packages.txt
spiir_p_astro-1.0.1.dist-info/top_level.txt
spiir_p_astro-1.0.1.dist-info/RECORD
