Metadata-Version: 2.1
Name: spiir-p-astro
Version: 1.0.1
Summary: Low-latency classification of GW triggers from compact binary coalescence
Home-page: https://lscsoft.docs.ligo.org/p-astro/
Author: Shasvath Kapadia, Deep Chatterjee, Shaon Ghosh
Author-email: shasvath.kapadia@ligo.org, deep.chatterjee@ligo.org, shaon.ghosh@ligo.org
Maintainer: Deep Chatterjee
Maintainer-email: deep.chatterjee@ligo.org
License: GNU General Public License Version 3
Classifier: Programming Language :: Python :: 3
Classifier: Operating System :: OS Independent
Classifier: Topic :: Internet
Classifier: Topic :: Scientific/Engineering :: Astronomy
Classifier: Topic :: Scientific/Engineering :: Physics
Requires-Python: >=3.7
License-File: LICENSE
Requires-Dist: astropy
Requires-Dist: lalsuite
Requires-Dist: numpy
Requires-Dist: python-ligo-lw
Requires-Dist: scipy
Requires-Dist: h5py
